holocron/__init__.py
holocron/__main__.py
holocron/config.py
holocron/logger.py
holocron/mirror.py
holocron/utils.py
holocron/providers/__init__.py
holocron/providers/base.py
holocron/providers/github.py
holocron/providers/gitlab.py
holocron_sync-1.1.5.dist-info/METADATA
holocron_sync-1.1.5.dist-info/WHEEL
holocron_sync-1.1.5.dist-info/entry_points.txt
holocron_sync-1.1.5.dist-info/licenses/LICENSE
holocron_sync-1.1.5.dist-info/RECORD
