Metadata-Version: 2.4
Name: holocron-sync
Version: 1.1.5
Summary: Holocron: The Ultimate Git Mirroring Tool
License-File: LICENSE
Requires-Python: >=3.9
Requires-Dist: python-dotenv
Requires-Dist: requests>=2.28.0
